odoo/addons/stock_lot_production_date/README.rst
odoo/addons/stock_lot_production_date/__init__.py
odoo/addons/stock_lot_production_date/__manifest__.py
odoo/addons/stock_lot_production_date/i18n/ca.po
odoo/addons/stock_lot_production_date/i18n/es.po
odoo/addons/stock_lot_production_date/i18n/fr.po
odoo/addons/stock_lot_production_date/i18n/it.po
odoo/addons/stock_lot_production_date/i18n/stock_lot_production_date.pot
odoo/addons/stock_lot_production_date/models/__init__.py
odoo/addons/stock_lot_production_date/models/stock_lot.py
odoo/addons/stock_lot_production_date/readme/CONTRIBUTORS.md
odoo/addons/stock_lot_production_date/readme/CREDITS.md
odoo/addons/stock_lot_production_date/readme/DESCRIPTION.md
odoo/addons/stock_lot_production_date/readme/USAGE.md
odoo/addons/stock_lot_production_date/static/description/icon.png
odoo/addons/stock_lot_production_date/static/description/index.html
odoo/addons/stock_lot_production_date/static/description/lot.png
odoo/addons/stock_lot_production_date/views/stock_lot.xml
odoo_addon_stock_lot_production_date-18.0.1.0.0.2.dist-info/METADATA
odoo_addon_stock_lot_production_date-18.0.1.0.0.2.dist-info/WHEEL
odoo_addon_stock_lot_production_date-18.0.1.0.0.2.dist-info/top_level.txt
odoo_addon_stock_lot_production_date-18.0.1.0.0.2.dist-info/RECORD
